libnetworkit.dylib
networkit-11.2.1.dist-info/RECORD
networkit-11.2.1.dist-info/WHEEL
networkit-11.2.1.dist-info/top_level.txt
networkit-11.2.1.dist-info/METADATA
include/tlx/timestamp.hpp
include/tlx/logger.hpp
include/tlx/container.hpp
include/tlx/thread_pool.hpp
include/tlx/cmdline_parser.hpp
include/tlx/thread_barrier_spin.hpp
include/tlx/semaphore.hpp
include/tlx/port.hpp
include/tlx/backtrace.hpp
include/tlx/die.hpp
include/tlx/multi_timer.hpp
include/tlx/algorithm.hpp
include/tlx/meta.hpp
include/tlx/counting_ptr.hpp
include/tlx/version.hpp
include/tlx/math.hpp
include/tlx/siphash.hpp
include/tlx/unused.hpp
include/tlx/thread_barrier_mutex.hpp
include/tlx/allocator_base.hpp
include/tlx/string.hpp
include/tlx/sort.hpp
include/tlx/simple_vector.hpp
include/tlx/digest.hpp
include/tlx/vector_free.hpp
include/tlx/stack_allocator.hpp
include/tlx/define.hpp
include/tlx/delegate.hpp
include/tlx/logger/unordered_map.hpp
include/tlx/logger/array.hpp
include/tlx/logger/map.hpp
include/tlx/logger/all.hpp
include/tlx/logger/tuple.hpp
include/tlx/logger/set.hpp
include/tlx/logger/deque.hpp
include/tlx/logger/wrap_unprintable.hpp
include/tlx/logger/unordered_set.hpp
include/tlx/logger/core.hpp
include/tlx/define/attribute_always_inline.hpp
include/tlx/define/attribute_packed.hpp
include/tlx/define/attribute_format_printf.hpp
include/tlx/define/endian.hpp
include/tlx/define/attribute_warn_unused_result.hpp
include/tlx/define/visibility_hidden.hpp
include/tlx/define/constexpr.hpp
include/tlx/define/likely.hpp
include/tlx/define/attribute_fallthrough.hpp
include/tlx/define/deprecated.hpp
include/tlx/sort/parallel_mergesort.hpp
include/tlx/sort/strings.hpp
include/tlx/sort/strings_parallel.hpp
include/tlx/sort/strings/string_ptr.hpp
include/tlx/sort/strings/sample_sort_tools.hpp
include/tlx/sort/strings/radix_sort.hpp
include/tlx/sort/strings/parallel_sample_sort.hpp
include/tlx/sort/strings/string_set.hpp
include/tlx/sort/strings/insertion_sort.hpp
include/tlx/sort/strings/multikey_quicksort.hpp
include/tlx/sort/networks/cswap.hpp
