Metadata-Version: 2.4
Name: networkit
Version: 11.2.1
Summary: NetworKit is a toolbox for high-performance network analysis
Home-page: https://networkit.github.io/
Download-URL: https://pypi.python.org/pypi/networkit
Author: Christian L. Staudt, Henning Meyerhenke
Author-email: christian.staudt@kit.edu, meyerhenke@kit.edu
License: Copyright (c) 2013-2022 Henning Meyerhenke, NetworKit Contributors
Project-URL: homepage, https://networkit.github.io/
Project-URL: documentation, https://networkit.github.io/dev-docs/index.html
Project-URL: repository, https://github.com/networkit/networkit
Project-URL: changelog, https://github.com/networkit/networkit/blob/master/CHANGES.md
Keywords: graph algorithm,network analysis,social network
Platform: any
Classifier: Development Status :: 5 - Production/Stable
Classifier: Environment :: Console
Classifier: Environment :: Web Environment
Classifier: Environment :: Other Environment
Classifier: Framework :: IPython
Classifier: Intended Audience :: Developers
Classifier: Intended Audience :: End Users/Desktop
Classifier: Intended Audience :: Science/Research
Classifier: License :: OSI Approved :: MIT License
Classifier: Natural Language :: English
Classifier: Operating System :: OS Independent
Classifier: Programming Language :: C++
Classifier: Programming Language :: Python :: 3 :: Only
Classifier: Topic :: Software Development :: Libraries :: Python Modules
Classifier: Topic :: Scientific/Engineering :: Bio-Informatics
Classifier: Topic :: Scientific/Engineering :: Chemistry
Classifier: Topic :: Scientific/Engineering :: Information Analysis
Classifier: Topic :: Scientific/Engineering :: Mathematics
Classifier: Topic :: Scientific/Engineering :: Visualization
Requires-Python: >=3.10
License-File: License.txt
Requires-Dist: scipy
Requires-Dist: numpy
Requires-Dist: tabulate
Dynamic: author-email
Dynamic: download-url
Dynamic: home-page
Dynamic: license-file
Dynamic: platform
